{
  "onlineState": {
    "0": "Unknown",
    "1": "Online",
    "2": "Offline"
  },
  "connectState": {
    "-1": "Unknown",
    "0": "Disconnected",
    "1": "Connected"
  },
  "vehicleState": {
    "0": "Standby",
    "1": "Active",
    "2": "Unknown"
  },
  "powerGear": {
    "0": "Unknown",
    "1": "Parked",
    "3": "Drive"
  },
  "airRunState": {
    "0": "External",
    "1": "Internal",
    "2": "Outside Fresh"
  },
  "seatHeatVentState": {
    "0": "Off",
    "1": "Level 1",
    "2": "Low",
    "3": "High"
  },
  "chargingState": {
    "-1": "Disconnected",
    "0": "Not Charging",
    "1": "Charging",
    "15": "Gun Connected"
  },
  "doorOpenState": {
    "0": "Closed",
    "1": "Open"
  },
  "lockState": {
    "0": "Unknown",
    "1": "Unlocked",
    "2": "Locked"
  },
  "windowState": {
    "0": "Unknown",
    "1": "Closed",
    "2": "Open"
  },
  "tirePressUnit": {
    "1": "bar",
    "2": "psi",
    "3": "kPa"
  },
  "tireStatus": {
    "0": "Normal"
  },
  "controlState": {
    "0": "Pending",
    "1": "Success",
    "2": "Failure"
  },
  "energyType": {
    "0": "EV",
    "1": "PHEV",
    "2": "Hybrid"
  },
  "empowerType": {
    "-1": "Shared User",
    "2": "Owner"
  },
  "permissionStatus": {
    "2": "Full Permissions",
    "3": "Full Permissions"
  },
  "acSwitch": {
    "0": "Off",
    "1": "On"
  },
  "cycleChoice": {
    "0": "Internal Recirculation",
    "1": "External Air"
  },
  "defrostStatus": {
    "0": "Off",
    "1": "On"
  },
  "refrigeratorState": {
    "0": "Off",
    "1": "On"
  },
  "refrigeratorDoorState": {
    "0": "Closed",
    "1": "Open"
  },
  "sentryStatus": {
    "0": "Off",
    "1": "On",
    "2": "Active"
  },
  "batteryHeatState": {
    "0": "Off",
    "1": "On"
  },
  "chargeHeatState": {
    "0": "Off",
    "1": "On"
  },
  "upgradeStatus": {
    "0": "None",
    "1": "Available",
    "2": "In Progress"
  },
  "warningState": {
    "0": "Normal",
    "1": "Warning",
    "2": "Error"
  },
  "epb": {
    "0": "Released",
    "1": "Engaged"
  },
  "gpsState": {
    "0": "Invalid",
    "1": "Valid"
  },
  "bookingChargeState": {
    "0": "Off",
    "1": "Scheduled"
  },
  "bookingDepartureState": {
    "0": "Off",
    "1": "Scheduled"
  },
  "smartChargeState": {
    "0": "Off",
    "1": "Active"
  },
  "smartJourneyState": {
    "0": "Off",
    "1": "Active"
  },
  "safeCharge": {
    "false": "Off",
    "true": "On"
  },
  "batteryHeatStatus": {
    "0": "Off",
    "1": "On"
  },
  "airStats": {
    "0": "Off",
    "1": "On"
  },
  "batteryHeat": {
    "0": "Off",
    "1": "On"
  },
  "res": {
    "0": "Pending",
    "1": "Failure",
    "2": "Success"
  },
  "airState": {
    "0": "Off",
    "1": "On"
  },
  "chargeStatus": {
    "0": "Not Charging",
    "1": "Charging"
  },
  "engineSt": {
    "0": "Off",
    "1": "On"
  },
  "doorLockStatus": {
    "1": "Unlocked",
    "2": "Locked"
  },
  "bonnetStatus": {
    "0": "Open",
    "2": "Closed"
  },
  "bootStatus": {
    "0": "Open",
    "2": "Closed"
  }
}
